vidtext/__init__.py
vidtext/directory.py
vidtext/image_utils.py
vidtext/imagesource.py
vidtext/text.py
vidtext/textTovideo.py
vidtext-1.1.dist-info/LICENSE
vidtext-1.1.dist-info/METADATA
vidtext-1.1.dist-info/WHEEL
vidtext-1.1.dist-info/top_level.txt
vidtext-1.1.dist-info/RECORD
