Metadata-Version: 2.1
Name: vidtext
Version: 1.1
Summary: This Project or Package Is Made for to Convert the Text to Video
Home-page: https://github.com/anubhavshakya/vidtext
Author: Anubhav Shakya
Author-email: inbox.anubhavshakya@gmail.com
License: MIT
Platform: UNKNOWN
Classifier: Development Status :: 4 - Beta
Classifier: Intended Audience :: System Administrators
Classifier: License :: OSI Approved :: Apache Software License
Classifier: Programming Language :: Python :: 3
Requires-Dist: pillow
Requires-Dist: google-images-download
Requires-Dist: rake-nltk
Requires-Dist: opencv-python
